findlike/__init__.py
findlike/__main__.py
findlike/cli.py
findlike/constants.py
findlike/format.py
findlike/markup.py
findlike/preprocessing.py
findlike/utils.py
findlike/wrappers.py
findlike-2.1.0.dist-info/licenses/LICENSE
findlike-2.1.0.dist-info/METADATA
findlike-2.1.0.dist-info/WHEEL
findlike-2.1.0.dist-info/entry_points.txt
findlike-2.1.0.dist-info/top_level.txt
findlike-2.1.0.dist-info/RECORD
