Metadata-Version: 2.4
Name: findlike
Version: 2.1.0
Summary: findlike is a package to retrieve similar documents
Author-email: Bruno Arine <bruno.arine@runbox.com>
Project-URL: Homepage, http://www.github.com/brunoarine/findlike
Project-URL: Repository, https://github.com/brunoarine/findlike.git
Project-URL: Bug Tracker, http://www.github.com/brunoarine/findlike/issues
Classifier: Programming Language :: Python :: 3
Classifier: Operating System :: OS Independent
Requires-Python: >=3.9
License-File: LICENSE
Requires-Dist: nltk>=3.9.1
Requires-Dist: numpy~=1.26.4
Requires-Dist: scikit-learn>=1.1.0
Requires-Dist: rank-bm25>=0.2.2
Requires-Dist: stop-words>=2018.7.23
Requires-Dist: click>=8.1.8
Dynamic: license-file
